rb_autocomplete_contains/__init__.py
rb_autocomplete_contains/extension.py
rb_autocomplete_contains/templates/autocomplete_contains/modify_field.html
rb_autocomplete_contains-2020.4.11.dist-info/LICENSE
rb_autocomplete_contains-2020.4.11.dist-info/METADATA
rb_autocomplete_contains-2020.4.11.dist-info/WHEEL
rb_autocomplete_contains-2020.4.11.dist-info/entry_points.txt
rb_autocomplete_contains-2020.4.11.dist-info/top_level.txt
rb_autocomplete_contains-2020.4.11.dist-info/RECORD
