Metadata-Version: 2.1
Name: rb-autocomplete-contains
Version: 2020.4.11
Summary: Review Board extension to enhance review groups autocomplete
Home-page: https://github.com/erijo/rb-autocomplete-contains
Author: Erik Johansson
Author-email: erik@ejohansson.se
License: UNKNOWN
Platform: UNKNOWN
Classifier: Development Status :: 5 - Production/Stable
Classifier: Intended Audience :: Developers
Classifier: Operating System :: OS Independent
Classifier: Programming Language :: Python :: 2
Classifier: Programming Language :: Python :: 3
Classifier: License :: OSI Approved :: MIT License
Classifier: Topic :: Software Development :: Quality Assurance
